JavaKuaisuJiaochengVamei/README.md
JavaKuaisuJiaochengVamei/__init__.py
JavaKuaisuJiaochengVamei/__main__.py
JavaKuaisuJiaochengVamei/file.epub
JavaKuaisuJiaochengVamei/index.html
JavaKuaisuJiaochengVamei/css/__init__.py
JavaKuaisuJiaochengVamei/css/annotations.css
JavaKuaisuJiaochengVamei/css/main.css
JavaKuaisuJiaochengVamei/css/normalize.css
JavaKuaisuJiaochengVamei/css/popup.css
JavaKuaisuJiaochengVamei/font/__init__.py
JavaKuaisuJiaochengVamei/font/fontello.eot
JavaKuaisuJiaochengVamei/font/fontello.svg
JavaKuaisuJiaochengVamei/font/fontello.ttf
JavaKuaisuJiaochengVamei/font/fontello.woff
JavaKuaisuJiaochengVamei/img/__init__.py
JavaKuaisuJiaochengVamei/img/annotator-glyph-sprite.png
JavaKuaisuJiaochengVamei/img/annotator-icon-sprite.png
JavaKuaisuJiaochengVamei/img/apple-touch-icon.png
JavaKuaisuJiaochengVamei/img/cancelfullscreen.png
JavaKuaisuJiaochengVamei/img/close.png
JavaKuaisuJiaochengVamei/img/fullscreen.png
JavaKuaisuJiaochengVamei/img/loader.gif
JavaKuaisuJiaochengVamei/img/menu-icon.png
JavaKuaisuJiaochengVamei/img/save.png
JavaKuaisuJiaochengVamei/img/saved.png
JavaKuaisuJiaochengVamei/img/settings-s.png
JavaKuaisuJiaochengVamei/img/settings.png
JavaKuaisuJiaochengVamei/img/star.png
JavaKuaisuJiaochengVamei/js/__init__.py
JavaKuaisuJiaochengVamei/js/epub.js
JavaKuaisuJiaochengVamei/js/epub.min.js
JavaKuaisuJiaochengVamei/js/epub.min.map
JavaKuaisuJiaochengVamei/js/hooks.min.js
JavaKuaisuJiaochengVamei/js/hooks.min.map
JavaKuaisuJiaochengVamei/js/reader.js
JavaKuaisuJiaochengVamei/js/reader.js.map
JavaKuaisuJiaochengVamei/js/reader.min.js
JavaKuaisuJiaochengVamei/js/reader.min.map
JavaKuaisuJiaochengVamei/js/hooks/__init__.py
JavaKuaisuJiaochengVamei/js/hooks/extensions/__init__.py
JavaKuaisuJiaochengVamei/js/hooks/extensions/highlight.js
JavaKuaisuJiaochengVamei/js/libs/__init__.py
JavaKuaisuJiaochengVamei/js/libs/jquery.min.js
JavaKuaisuJiaochengVamei/js/libs/localforage.min.js
JavaKuaisuJiaochengVamei/js/libs/screenfull.js
java_kuaisu_jiaocheng_vamei-2024.3.2.0.dist-info/METADATA
java_kuaisu_jiaocheng_vamei-2024.3.2.0.dist-info/WHEEL
java_kuaisu_jiaocheng_vamei-2024.3.2.0.dist-info/entry_points.txt
java_kuaisu_jiaocheng_vamei-2024.3.2.0.dist-info/top_level.txt
java_kuaisu_jiaocheng_vamei-2024.3.2.0.dist-info/RECORD
